.coveragerc
.travis.yml
LICENSE
MANIFEST.in
README.rst
setup.py
Mopidy_Local_Whoosh.egg-info/PKG-INFO
Mopidy_Local_Whoosh.egg-info/SOURCES.txt
Mopidy_Local_Whoosh.egg-info/dependency_links.txt
Mopidy_Local_Whoosh.egg-info/entry_points.txt
Mopidy_Local_Whoosh.egg-info/not-zip-safe
Mopidy_Local_Whoosh.egg-info/requires.txt
Mopidy_Local_Whoosh.egg-info/top_level.txt
mopidy_local_whoosh/__init__.py
mopidy_local_whoosh/ext.conf
mopidy_local_whoosh/library.py
tests/__init__.py
tests/test_extension.py