Metadata-Version: 1.1
Name: Mopidy-Local-Whoosh
Version: 0.1.0
Summary: Whoosh local library extension.
Home-page: https://github.com/mopidy/mopidy-local-whoosh
Author: Thomas Adamcik
Author-email: thomas@adamcik.no
License: Apache License, Version 2.0
Platform: UNKNOWN
Classifier: Environment :: No Input/Output (Daemon)
Classifier: Intended Audience :: End Users/Desktop
Classifier: License :: OSI Approved :: Apache Software License
Classifier: Operating System :: OS Independent
Classifier: Programming Language :: Python :: 2
Classifier: Topic :: Multimedia :: Sound/Audio :: Players
